metalearning_class/__init__.py
metalearning_class/_internal/__init__.py
metalearning_class/_internal/conn.py
metalearning_class/_internal/metadata.py
metalearning_class/model/__init__.py
metalearning_class/model/mtl_class.py
metalearning_class/modules/__init__.py
metalearning_class/modules/functions.py
metalearning_class/modules/robust_network.py
metalearning_class/modules/transformer.py
metalearning_class/modules/transformer_utils.py
metalearning_class-0.1.0.dist-info/licenses/LICENSE
metalearning_class-0.1.0.dist-info/METADATA
metalearning_class-0.1.0.dist-info/WHEEL
metalearning_class-0.1.0.dist-info/top_level.txt
metalearning_class-0.1.0.dist-info/RECORD
