Metadata-Version: 2.4
Name: metalearning_class
Version: 0.1.0
Summary: A library for meta-learning in Python with neural networks and transformers.
Author: Gabriel Alves Castro, João Bizzo Brandt, Lucca Huguet
Maintainer: Panaceia
License: # Sofon Client Library & Vendor License (SCLVL)
Project-URL: Homepage, https://github.com/panaceia/metalearning
Project-URL: Documentation, https://github.com/panaceia/metalearning#readme
Project-URL: Bug_Tracker, https://github.com/panaceia/metalearning/issues
Project-URL: Changelog, https://github.com/panaceia/metalearning/releases
Keywords: machine learning,metalearning,meta-learning,neural networks,transformers
Classifier: Development Status :: 3 - Alpha
Classifier: Intended Audience :: Science/Research
Classifier: License :: Other/Proprietary License
Classifier: Programming Language :: Python :: 3
Classifier: Programming Language :: Python :: 3.8
Classifier: Programming Language :: Python :: 3.9
Classifier: Programming Language :: Python :: 3.10
Classifier: Programming Language :: Python :: 3.11
Classifier: Topic :: Scientific/Engineering :: Artificial Intelligence
Requires-Python: >=3.8
License-File: LICENSE
Requires-Dist: numpy>=1.21.0
Requires-Dist: pandas>=1.3.0
Requires-Dist: tensorflow>=2.8.0
Requires-Dist: scikit-learn>=1.0.0
Requires-Dist: dill==0.4.0
Requires-Dist: matplotlib==3.10.5
Requires-Dist: si-prefix==1.3.3
Provides-Extra: dev
Requires-Dist: pytest>=7.0; extra == "dev"
Requires-Dist: pytest-cov>=3.0; extra == "dev"
Requires-Dist: black>=22.0; extra == "dev"
Requires-Dist: flake8>=4.0; extra == "dev"
Requires-Dist: mypy>=0.900; extra == "dev"
Requires-Dist: ipython>=8.0; extra == "dev"
Provides-Extra: docs
Requires-Dist: sphinx>=5.0; extra == "docs"
Requires-Dist: furo>=2022.6.0; extra == "docs"
Requires-Dist: sphinx-copybutton>=0.5.0; extra == "docs"
Provides-Extra: test
Requires-Dist: pytest>=7.0; extra == "test"
Requires-Dist: pytest-mock>=3.0; extra == "test"
Requires-Dist: pytest-xdist>=3.0; extra == "test"
Dynamic: license-file
